kupujemprodajem_api/.gitignore
kupujemprodajem_api/__init__.py
kupujemprodajem_api/api.py
kupujemprodajem_api/exceptions.py
kupujemprodajem_api/models.py
kupujemprodajem_api-0.1.0.dist-info/LICENSE.txt
kupujemprodajem_api-0.1.0.dist-info/WHEEL
kupujemprodajem_api-0.1.0.dist-info/METADATA
kupujemprodajem_api-0.1.0.dist-info/RECORD
